jrun/__init__.py
jrun/_base.py
jrun/interfaces.py
jrun/job_submitter.py
jrun/job_viewer.py
jrun/jrun_server_v2.py
jrun/jweb_server.py
jrun/main.py
sdagger-1.0.0.dist-info/METADATA
sdagger-1.0.0.dist-info/WHEEL
sdagger-1.0.0.dist-info/entry_points.txt
sdagger-1.0.0.dist-info/top_level.txt
sdagger-1.0.0.dist-info/RECORD
