Metadata-Version: 2.4
Name: sdagger
Version: 1.0.0
Requires-Dist: tabulate>=0.9.0
Requires-Dist: PyYAML>=6.0
Requires-Dist: appdirs>=1.4.4
Dynamic: requires-dist
